<?xml version="1.0" encoding="UTF-8"?>
<site>
	<description>To install these features, point Eclipse at this site.</description>
	<!-- JBoss Tools vpe Nightly Build Update Site -->
	<!--VPE-->
	<category-def label="JBoss Tools Browsersim Nightly Build Update Site" name="JBoss Tools Browsersim Nightly Build Update Site">
		<description>JBoss Tools Browsersim Nightly Build Update Site: contains all features in this build.</description>
	</category-def>

	<!--BrowserSim-->
	<feature url="features/org.jboss.tools.browsersim.feature_3.8.4.v20170530-0706.jar" id="org.jboss.tools.browsersim.feature" version="3.8.4.v20170530-0706">
		<category name="JBoss Tools vpe Nightly Build Update Site"/>
	</feature>
	<feature url="features/org.jboss.tools.browsersim.feature.source_3.8.4.v20170530-0706.jar" id="org.jboss.tools.browsersim.feature.source" version="3.8.4.v20170530-0706">
		<category name="JBoss Tools vpe Nightly Build Update Site"/>
	</feature>
</site>
